hype/__init__.py
hype/function.py
hype/job.py
hype/task.py
hype/cli/__init__.py
hype/cli/utils.py
hype/cli/commands/__init__.py
hype/cli/commands/run.py
hype/cli/commands/serve.py
hype/gui/__init__.py
hype/gui/gradio.py
hype/http/__init__.py
hype/http/accept.py
hype/http/prefer.py
hype/http/problem.py
hype/tools/__init__.py
hype/tools/anthropic.py
hype/tools/ollama.py
hype/tools/openai.py
hype-0.0.1.dist-info/METADATA
hype-0.0.1.dist-info/WHEEL
hype-0.0.1.dist-info/entry_points.txt
hype-0.0.1.dist-info/licenses/LICENSE.md
hype-0.0.1.dist-info/RECORD
