Metadata-Version: 2.4
Name: hype
Version: 0.0.1
License-File: LICENSE.md
Requires-Python: >=3.10
Requires-Dist: click>=8.0.0
Requires-Dist: docstring-parser>=0.16
Requires-Dist: fastapi>=0.100.0
Requires-Dist: httpx>=0.27.2
Requires-Dist: pydantic>=2.0
Requires-Dist: python-multipart
Requires-Dist: uvicorn>=0.27.0
